{
  "id": "spacecho",
  "name": "Space Echo",
  "version": "0.2.1",
  "description": "RE-201 style tape delay",
  "author": "Charles Vestal",
  "dsp": "spacecho.so",
  "api_version": 2,
  "capabilities": {
    "chainable": true,
    "component_type": "audio_fx",
    "chain_params": [
      {"key": "time", "name": "Time", "type": "float", "min": 0.0, "max": 1.0, "default": 0.4, "step": 0.05},
      {"key": "feedback", "name": "Feedback", "type": "float", "min": 0.0, "max": 1.0, "default": 0.4, "step": 0.05},
      {"key": "mix", "name": "Mix", "type": "float", "min": 0.0, "max": 1.0, "default": 0.35, "step": 0.05},
      {"key": "tone", "name": "Tone", "type": "float", "min": 0.0, "max": 1.0, "default": 0.6, "step": 0.05},
      {"key": "saturation", "name": "Saturation", "type": "float", "min": 0.0, "max": 1.0, "default": 0.0, "step": 0.05}
    ]
  }
}
